#### 变量字节码

##### java 定义成员变量
下面是类的成员变量初始化时，字节码分析
``` java
Classfile /Users/wm/git-code/algorithm/algorithm-learn/jvm/SimpleClass.class
  Last modified 2017-5-22; size 242 bytes
  MD5 checksum 0f6bfdde3856316225c9f9b4a460d330
  Compiled from "SimpleClass.java"
public class SimpleClass
  minor version: 0
  major version: 52
  flags: ACC_PUBLIC, ACC_SUPER
Constant pool:
   #1 = Methodref          #4.#13         // java/lang/Object."<init>":()V
   #2 = Fieldref           #3.#14         // SimpleClass.simpleField:I
   #3 = Class              #15            // SimpleClass
   #4 = Class              #16            // java/lang/Object
   #5 = Utf8               simpleField
   #6 = Utf8               I
   #7 = Utf8               <init>
   #8 = Utf8               ()V
   #9 = Utf8               Code
  #10 = Utf8               LineNumberTable
  #11 = Utf8               SourceFile
  #12 = Utf8               SimpleClass.java
  #13 = NameAndType        #7:#8          // "<init>":()V
  #14 = NameAndType        #5:#6          // simpleField:I
  #15 = Utf8               SimpleClass
  #16 = Utf8               java/lang/Object
{
  public int simpleField;
    descriptor: I
    flags: ACC_PUBLIC

  public SimpleClass();
    descriptor: ()V
    flags: ACC_PUBLIC
    Code:
      stack=2, locals=1, args_size=1
         0: aload_0
         1: invokespecial #1                  // Method java/lang/Object."<init>":()V
         4: aload_0
         5: bipush        100
         7: putfield      #2                  // Field simpleField:I
        10: return
      LineNumberTable:
        line 5: 0
        line 7: 4
}
SourceFile: "SimpleClass.java"
```
上面是 javap分析的字节码信息，分析下一些指令
`aload_0`:从局部变量表中的 指定位置 装载出来一个对象引用到操作数栈的栈顶位置，
上面的例子中虽然没写构造函数，但是成员变量初始化实际也是在编译器默认构造函数中执行的，所以第一个变量实际指向的是 this

`invokespecial`:这指令用于调用实例的初始化方法，包括私有方法以及当前类的父类方法。它同样属于一组以不同方式来调用方法的操作码，
这些操作码包括invokedynamic、invokeinterface、invokespecial、invokestatic和invokevirtual。invokespecial是用于调用父类构造方法的指令，例如java.lang.Object的构造方法。

`bipush`: 把一个int的值放入到操作数栈中，

`putfield`:首先，从常量池中获取到这个成员变量的引用， 然后，从操作数栈中弹出一个成员变量的值 和 其对应的是哪个对象，
例子中，首先得到一个引用 `#2 = Fieldref`，然后从操作数栈中弹出 100 和 this,最终这个字段就被赋值为100


##### java 类常量











